srpp/__init__.py
srpp/srpp.py
srpp/params/corr2010_curr.csv
srpp/params/cpi.csv
srpp/params/cpp_history.xlsx
srpp/params/cpp_history_full.xlsx
srpp/params/cppyear.csv
srpp/params/qpp_history.xlsx
srpp-0.7.0.dist-info/LICENSE
srpp-0.7.0.dist-info/METADATA
srpp-0.7.0.dist-info/WHEEL
srpp-0.7.0.dist-info/top_level.txt
srpp-0.7.0.dist-info/RECORD
