Metadata-Version: 2.1
Name: srpp
Version: 0.7.0
Summary: Module pour simuler prestations pensions publiques Canada
Home-page: https://creei-models.github.io/srpp/
Author: Francois Laliberte-Auger, Nicholas-James Clavet, Pierre-Carl Michaud
Author-email: francois.laliberte-auger@hec.ca
License: UNKNOWN
Platform: UNKNOWN
Classifier: Programming Language :: Python :: 3
Classifier: License :: OSI Approved :: MIT License
Classifier: Operating System :: OS Independent
Requires-Python: >=3.6
License-File: LICENSE
Requires-Dist: pandas
Requires-Dist: numpy
Requires-Dist: xlrd
